gsmservice_gateway/__init__.py
gsmservice_gateway/_hooks/__init__.py
gsmservice_gateway/_hooks/registration.py
gsmservice_gateway/_hooks/sdkhooks.py
gsmservice_gateway/_hooks/types.py
gsmservice_gateway/_version.py
gsmservice_gateway/accounts.py
gsmservice_gateway/basesdk.py
gsmservice_gateway/common.py
gsmservice_gateway/httpclient.py
gsmservice_gateway/incoming.py
gsmservice_gateway/mms.py
gsmservice_gateway/models/__init__.py
gsmservice_gateway/models/accountresponse.py
gsmservice_gateway/models/addsenderop.py
gsmservice_gateway/models/cancelledmessage.py
gsmservice_gateway/models/cancelmessagesop.py
gsmservice_gateway/models/clienterror.py
gsmservice_gateway/models/deletesenderop.py
gsmservice_gateway/models/errorresponse.py
gsmservice_gateway/models/errorresponse_error.py
gsmservice_gateway/models/getincomingmessagesop.py
gsmservice_gateway/models/getmessagesop.py
gsmservice_gateway/models/getmmspriceop.py
gsmservice_gateway/models/getsmspriceop.py
gsmservice_gateway/models/getsubaccountdetailsop.py
gsmservice_gateway/models/incomingmessage.py
gsmservice_gateway/models/listincomingmessagesop.py
gsmservice_gateway/models/listmessagesop.py
gsmservice_gateway/models/message.py
gsmservice_gateway/models/messagetype.py
gsmservice_gateway/models/mmsmessage.py
gsmservice_gateway/models/no_response_error.py
gsmservice_gateway/models/phonenumberwithcid.py
gsmservice_gateway/models/pingresponse.py
gsmservice_gateway/models/price.py
gsmservice_gateway/models/responsevalidationerror.py
gsmservice_gateway/models/sdkerror.py
gsmservice_gateway/models/security.py
gsmservice_gateway/models/sender.py
gsmservice_gateway/models/sender_input.py
gsmservice_gateway/models/sendmmsop.py
gsmservice_gateway/models/sendsmsop.py
gsmservice_gateway/models/setdefaultsenderop.py
gsmservice_gateway/models/smsmessage.py
gsmservice_gateway/models/smstype.py
gsmservice_gateway/outgoing.py
gsmservice_gateway/py.typed
gsmservice_gateway/sdk.py
gsmservice_gateway/sdkconfiguration.py
gsmservice_gateway-3.1.1.dist-info/LICENSE
gsmservice_gateway-3.1.1.dist-info/METADATA
gsmservice_gateway-3.1.1.dist-info/WHEEL
gsmservice_gateway-3.1.1.dist-info/RECORD
