Metadata-Version: 2.3
Name: gsmservice-gateway
Version: 3.1.1
Summary: Python Client SDK for Messaging Gateway SzybkiSMS.pl
Author: SzybkiSMS.pl
Requires-Python: >=3.9.2
Classifier: Programming Language :: Python :: 3
Classifier: Programming Language :: Python :: 3.10
Classifier: Programming Language :: Python :: 3.11
Classifier: Programming Language :: Python :: 3.12
Classifier: Programming Language :: Python :: 3.13
Requires-Dist: httpcore (>=1.0.9)
Requires-Dist: httpx (>=0.28.1)
Requires-Dist: pydantic (>=2.11.2)
